{"Bus": {"roof": false, "floor": true, "solid": false, "walls": false, "priority": 1, "roofColor": "#202020", "floorColor": "#f2f2f2", "roofHeight": 2.5, "wallsColor": "#a0a0a0", "wallsWidth": 0.1, "wallsHeight": 2.5}, "Road": {"roof": false, "floor": true, "solid": false, "walls": false, "priority": 1, "roofColor": "#202020", "floorColor": "#eeebc4", "roofHeight": 2.5, "wallsColor": "#a0a0a0", "wallsWidth": 0.1, "wallsHeight": 2.5}, "desk": {"roof": false, "floor": true, "solid": false, "walls": true, "priority": 12, "roofColor": "#202020", "floorColor": "#f2f2f2", "roofHeight": 2.5, "wallsColor": "#dcdddc", "wallsWidth": 0.1, "wallsHeight": 0.3}, "ramp": {"roof": false, "floor": true, "solid": false, "walls": false, "priority": 10, "roofColor": "#202020", "floorColor": "#d7ecf1", "roofHeight": 2.5, "wallsColor": "#a0a0a0", "wallsWidth": 0.1, "wallsHeight": 2.5}, "road": {"roof": false, "floor": false, "solid": false, "walls": false, "priority": 0, "roofColor": "#202020", "floorColor": "#ffffff", "roofHeight": 2.5, "wallsColor": "#a0a0a0", "wallsWidth": 0.1, "wallsHeight": 2.5}, "room": {"roof": false, "floor": true, "solid": false, "walls": true, "priority": 10, "roofColor": "#dd0a0a", "floorColor": "#f2f2f2", "roofHeight": 2.5, "wallsColor": "#dcdddc", "wallsWidth": 0.1, "wallsHeight": 2.5}, "Apron": {"roof": false, "floor": true, "solid": false, "walls": false, "priority": 1, "roofColor": "#202020", "floorColor": "#f2f2f2", "roofHeight": 2.5, "wallsColor": "#a0a0a0", "wallsWidth": 0.1, "wallsHeight": 2.5}, "Grass": {"roof": false, "floor": true, "solid": false, "walls": false, "priority": 1, "roofColor": "#202020", "floorColor": "#cedece", "roofHeight": 2.5, "wallsColor": "#a0a0a0", "wallsWidth": 0.1, "wallsHeight": 2.5}, "Kiosk": {"roof": false, "floor": true, "solid": false, "walls": true, "priority": 10, "roofColor": "#c4d9df", "floorColor": "#eeeeee", "wallsColor": "#d9dad9", "wallsHeight": 0.25}, "Level": {"roof": false, "floor": false, "solid": true, "walls": true, "priority": 0, "roofColor": "#202020", "floorColor": "#ffffff", "roofHeight": 2.5, "wallsColor": "#a0a0a0", "wallsWidth": 0.1, "wallsHeight": 2.5}, "Water": {"roof": false, "floor": true, "solid": false, "walls": false, "priority": 0, "roofColor": "#202020", "floorColor": "#e5f4fa", "roofHeight": 2.5, "wallsColor": "#a0a0a0", "wallsWidth": 0.1, "wallsHeight": 2.5}, "lobby": {"roof": false, "floor": false, "solid": false, "walls": true, "priority": 0, "roofColor": "#202020", "floorColor": "#606060", "roofHeight": 2.5, "wallsColor": "#dcdddc", "wallsWidth": 0.1, "wallsHeight": 2.5}, "indoor": {"floor": true, "walls": true, "priority": 10, "floorColor": "#ffffff", "wallsColor": "#bcbec2", "wallsHeight": 0.1}, "office": {"roof": false, "floor": true, "solid": false, "walls": true, "priority": 10, "roofColor": "#202020", "floorColor": "#f2f2f2", "roofHeight": 2.5, "wallsColor": "#dcdddc", "wallsWidth": 0.1, "wallsHeight": 2.5}, "stairs": {"roof": false, "floor": true, "solid": false, "walls": true, "priority": 10, "roofColor": "#c4d9df", "floorColor": "#d7ecf1", "roofHeight": 2.5, "wallsColor": "#b2c8ce", "wallsWidth": 0.1, "wallsHeight": 0.7}, "Parking": {"roof": false, "floor": true, "solid": false, "walls": false, "priority": 1, "roofColor": "#ece4d6", "floorColor": "#ece4d6", "roofHeight": 2.5, "wallsColor": "#a0a0a0", "wallsWidth": 0.1, "wallsHeight": 2.5}, "Walkway": {"roof": false, "floor": true, "solid": false, "walls": true, "priority": 10, "roofColor": "#c4d9df", "floorColor": "#ffffff", "wallsColor": "#dcdddc"}, "parking": {"roof": false, "floor": true, "solid": false, "walls": true, "priority": 10, "roofColor": "#202020", "floorColor": "#eeeeee", "roofHeight": 2.5, "wallsColor": "#bcbec2", "wallsWidth": 0.2, "wallsHeight": 0.2}, "walkway": {"roof": false, "floor": true, "solid": false, "walls": true, "priority": 12, "roofColor": "#202020", "floorColor": "#ffffff", "roofHeight": 2.5, "wallsColor": "#dcdddc", "wallsWidth": 0.1, "wallsHeight": 2.5}, "Building": {"roof": true, "floor": true, "solid": false, "walls": true, "priority": 0, "roofColor": "#202020", "floorColor": "#ffffff", "roofHeight": 2.5, "wallsColor": "#878787", "wallsWidth": 0.5, "wallsHeight": 0}, "__dark__": {"Bus": {"roof": false, "floor": true, "solid": false, "walls": false, "priority": 1, "roofColor": "#202020", "floorColor": "#f2f2f2", "roofHeight": 2.5, "wallsColor": "#a0a0a0", "wallsWidth": 0.1, "wallsHeight": 2.5}, "Road": {"roof": false, "floor": true, "solid": false, "walls": false, "priority": 1, "roofColor": "#202020", "floorColor": "#eeebc4", "roofHeight": 2.5, "wallsColor": "#a0a0a0", "wallsWidth": 0.1, "wallsHeight": 2.5}, "desk": {"roof": false, "floor": true, "solid": false, "walls": true, "priority": 12, "roofColor": "#202020", "floorColor": "#8894aa", "roofHeight": 2.5, "wallsColor": "#5e6c86", "wallsWidth": 0.1, "wallsHeight": 0.3}, "ramp": {"roof": false, "floor": true, "solid": false, "walls": false, "priority": 12, "roofColor": "#202020", "floorColor": "#d8f4ea", "roofHeight": 2.5, "wallsColor": "#a0a0a0", "wallsWidth": 0.1, "wallsHeight": 2.5}, "road": {"roof": false, "floor": false, "solid": false, "walls": false, "priority": 0, "roofColor": "#202020", "floorColor": "#ffffff", "roofHeight": 2.5, "wallsColor": "#a0a0a0", "wallsWidth": 0.1, "wallsHeight": 2.5}, "room": {"roof": false, "floor": true, "solid": false, "walls": true, "priority": 12, "roofColor": "#dd0a0a", "floorColor": "#8894aa", "roofHeight": 2.5, "wallsColor": "#5e6c86", "wallsWidth": 0.1, "wallsHeight": 2.5}, "Apron": {"roof": false, "floor": true, "solid": false, "walls": false, "priority": 1, "roofColor": "#202020", "floorColor": "#f2f2f2", "roofHeight": 2.5, "wallsColor": "#a0a0a0", "wallsWidth": 0.1, "wallsHeight": 2.5}, "Grass": {"roof": false, "floor": true, "solid": false, "walls": false, "priority": 1, "roofColor": "#202020", "floorColor": "#cedece", "roofHeight": 2.5, "wallsColor": "#a0a0a0", "wallsWidth": 0.1, "wallsHeight": 2.5}, "Kiosk": {"roof": false, "floor": true, "solid": false, "walls": true, "priority": 10, "roofColor": "#c4d9df", "floorColor": "#eeeeee", "wallsColor": "#d9dad9", "wallsHeight": 0.25}, "Level": {"roof": false, "floor": false, "solid": true, "walls": true, "priority": 0, "roofColor": "#202020", "floorColor": "#ffffff", "roofHeight": 2.5, "wallsColor": "#7f8ca4", "wallsWidth": 0.1, "wallsHeight": 2.5}, "Water": {"roof": false, "floor": true, "solid": false, "walls": false, "priority": 0, "roofColor": "#202020", "floorColor": "#e5f4fa", "roofHeight": 2.5, "wallsColor": "#a0a0a0", "wallsWidth": 0.1, "wallsHeight": 2.5}, "lobby": {"roof": false, "floor": true, "solid": false, "walls": true, "priority": 12, "roofColor": "#202020", "floorColor": "#c8ceda", "roofHeight": 2.5, "wallsColor": "#5e6c86", "wallsWidth": 0.1, "wallsHeight": 2.5}, "indoor": {"floor": true, "walls": true, "priority": 10, "floorColor": "#ffffff", "wallsColor": "#bcbec2", "wallsHeight": 0.1}, "office": {"roof": false, "floor": true, "solid": false, "walls": true, "priority": 12, "roofColor": "#202020", "floorColor": "#8894aa", "roofHeight": 2.5, "wallsColor": "#5e6c86", "wallsWidth": 0.1, "wallsHeight": 2.5}, "stairs": {"roof": false, "floor": true, "solid": false, "walls": true, "priority": 12, "roofColor": "#c4d9df", "floorColor": "#d8f4ea", "roofHeight": 2.5, "wallsColor": "#7fccb1", "wallsWidth": 0.1, "wallsHeight": 0.7}, "Parking": {"roof": false, "floor": true, "solid": false, "walls": false, "priority": 1, "roofColor": "#ece4d6", "floorColor": "#ece4d6", "roofHeight": 2.5, "wallsColor": "#a0a0a0", "wallsWidth": 0.1, "wallsHeight": 2.5}, "Walkway": {"roof": false, "floor": true, "solid": false, "walls": true, "priority": 11, "roofColor": "#c4d9df", "floorColor": "#c8ceda", "roofHeight": 2.5, "wallsColor": "#5e6c86", "wallsWidth": 0.1, "wallsHeight": 2.5}, "parking": {"roof": false, "floor": true, "solid": false, "walls": true, "priority": 10, "roofColor": "#202020", "floorColor": "#eeeeee", "roofHeight": 2.5, "wallsColor": "#bcbec2", "wallsWidth": 0.2, "wallsHeight": 0.2}, "walkway": {"roof": false, "floor": true, "solid": false, "walls": true, "priority": 120, "roofColor": "#202020", "floorColor": "#a9b3c6", "roofHeight": 2.5, "wallsColor": "#707379", "wallsWidth": 0.1, "wallsHeight": 2.5}, "Building": {"roof": true, "floor": true, "solid": false, "walls": true, "priority": 0, "roofColor": "#202020", "floorColor": "#ffffff", "roofHeight": 2.5, "wallsColor": "#878787", "wallsWidth": 0.5, "wallsHeight": 0}, "elevator": {"roof": true, "floor": true, "solid": false, "walls": true, "priority": 12, "roofColor": "#9bd5c1", "floorColor": "#d8f4ea", "roofHeight": 2.5, "wallsColor": "#7fccb1", "wallsWidth": 0.1, "wallsHeight": 2.5}, "restroom": {"roof": true, "floor": true, "solid": false, "walls": true, "priority": 10, "roofColor": "#e3d4ed", "floorColor": "#ede7f1", "roofHeight": 2.5, "wallsColor": "#d0b7e1", "wallsWidth": 0.1, "wallsHeight": 2.5}, "security": {"roof": false, "floor": true, "solid": false, "walls": false, "priority": 100, "roofColor": "#202020", "floorColor": "#f4c8cb", "roofHeight": 2.5, "wallsColor": "#a0a0a0", "wallsWidth": 0.1, "wallsHeight": 2.5}, "Aerodrome": {"roof": false, "floor": true, "solid": false, "walls": false, "priority": 0, "roofColor": "#202020", "floorColor": "#ededed", "roofHeight": 2.5, "wallsColor": "#a0a0a0", "wallsWidth": 0.1, "wallsHeight": 2.5}, "carrental": {"roof": false, "floor": true, "solid": false, "walls": false, "priority": 11, "roofColor": "#202020", "floorColor": "#f2f2f2", "roofHeight": 2.5, "wallsColor": "#dcdddc", "wallsWidth": 0.1, "wallsHeight": 2.5}, "escalator": {"roof": false, "floor": true, "solid": false, "walls": true, "priority": 12, "roofColor": "#c4d9df", "floorColor": "#d8f4ea", "roofHeight": 2.5, "wallsColor": "#7fccb1", "wallsWidth": 0.1, "wallsHeight": 0.5}, "furniture": {"floor": true, "solid": false, "walls": true, "priority": 10, "floorColor": "#d9dce7", "wallsColor": "#c7cbdd", "wallsHeight": 0.01}, "nonpublic": {"roof": true, "floor": false, "solid": true, "walls": true, "priority": 10, "roofColor": "#c1c1c1", "floorColor": "#606060", "roofHeight": 2.5, "wallsColor": "#5b698b", "wallsWidth": 0.1, "wallsHeight": 2.5}, "structure": {"roof": true, "floor": false, "solid": true, "walls": true, "priority": 12, "roofColor": "#e8e8e8", "floorColor": "#606060", "roofHeight": 2.5, "wallsColor": "#5e6c86", "wallsWidth": 0.1, "wallsHeight": 2.5}, "Minor Road": {"roof": false, "floor": true, "solid": false, "walls": false, "priority": 0, "roofColor": "#202020", "floorColor": "#f7f7f7", "roofHeight": 2.5, "wallsColor": "#a0a0a0", "wallsWidth": 0.1, "wallsHeight": 2.5}, "foodservice": {"roof": false, "floor": true, "solid": false, "walls": true, "priority": 12, "roofColor": "#202020", "floorColor": "#8894aa", "roofHeight": 2.5, "wallsColor": "#5e6c86", "wallsWidth": 0.1, "wallsHeight": 2.5}, "immigration": {"roof": false, "floor": false, "solid": false, "walls": false, "priority": 100, "roofColor": "#202020", "floorColor": "#fce6e8", "roofHeight": 2.5, "wallsColor": "#a0a0a0", "wallsWidth": 0.1, "wallsHeight": 2.5}, "mothersroom": {"roof": true, "floor": true, "solid": false, "walls": true, "priority": 12, "roofColor": "#8894aa", "floorColor": "#cad3e2", "roofHeight": 2.5, "wallsColor": "#5e6c86", "wallsWidth": 0.1, "wallsHeight": 2.5}, "opentobelow": {"roof": false, "floor": true, "solid": false, "walls": false, "priority": 12, "roofColor": "#ece4d6", "floorColor": "#575679", "roofHeight": 2.5, "wallsColor": "#dcdddc", "wallsWidth": 0.1, "wallsHeight": 2.5}, "unspecified": {"roof": false, "floor": true, "solid": false, "walls": true, "priority": 10, "roofColor": "#202020", "floorColor": "#8894aa", "roofHeight": 2.5, "wallsColor": "#5e6c86", "wallsWidth": 0.1, "wallsHeight": 2.5}, "waitingroom": {"roof": false, "floor": true, "solid": false, "walls": true, "priority": 13, "roofColor": "#202020", "floorColor": "#8894aa", "roofHeight": 2.5, "wallsColor": "#7f8ca4", "wallsWidth": 0.1, "wallsHeight": 2.5}, "baggageclaim": {"roof": false, "floor": false, "solid": false, "walls": false, "priority": 10, "roofColor": "#202020", "floorColor": "#d9dce7", "roofHeight": 2.5, "wallsColor": "#c9d1dd", "wallsWidth": 0.1, "wallsHeight": 0.5}, "checkin.desk": {"roof": false, "floor": true, "solid": false, "walls": true, "priority": 15, "roofColor": "#202020", "floorColor": "#d7ecf1", "roofHeight": 2.5, "wallsColor": "#b2c8ce", "wallsWidth": 0.1, "wallsHeight": 0.5}, "movingwalkway": {"roof": false, "floor": true, "solid": false, "walls": true, "priority": 12, "roofColor": "#202020", "floorColor": "#d8f4ea", "roofHeight": 2.5, "wallsColor": "#7fccb1", "wallsWidth": 0.1, "wallsHeight": 0.7}, "privatelounge": {"roof": false, "floor": true, "solid": false, "walls": true, "priority": 12, "roofColor": "#202020", "floorColor": "#8894aa", "roofHeight": 2.5, "wallsColor": "#5e6c86", "wallsWidth": 0.1, "wallsHeight": 2.5}, "restroom.male": {"roof": true, "floor": true, "solid": false, "walls": true, "priority": 10, "roofColor": "#e3d4ed", "floorColor": "#ede7f1", "roofHeight": 2.5, "wallsColor": "#d0b7e1", "wallsWidth": 0.1, "wallsHeight": 2.5}, "baggagecarousel": {"roof": false, "floor": true, "solid": false, "walls": true, "priority": 13, "roofColor": "#202020", "floorColor": "#d7ecf1", "roofHeight": 2.5, "wallsColor": "#b2c8ce", "wallsWidth": 0.1, "wallsHeight": 0.5}, "restroom.female": {"roof": true, "floor": true, "solid": false, "walls": true, "priority": 10, "roofColor": "#e3d4ed", "floorColor": "#ede7f1", "roofHeight": 2.5, "wallsColor": "#d0b7e1", "wallsWidth": 0.1, "wallsHeight": 2.5}, "restroom.unisex": {"roof": true, "floor": true, "solid": false, "walls": true, "priority": 10, "roofColor": "#e3d4ed", "floorColor": "#ede7f1", "roofHeight": 2.5, "wallsColor": "#d0b7e1", "wallsWidth": 0.1, "wallsHeight": 2.5}, "Building_basemap": {"roof": false, "floor": true, "solid": false, "walls": false, "priority": 0, "roofColor": "#202020", "floorColor": "#ece4d6", "roofHeight": 2.5, "wallsColor": "#a0a0a0", "wallsWidth": 0.1, "wallsHeight": 2.5}, "84578764-8448-4191-b2af-f518cbfbafe7": {"roof": false, "floor": false, "solid": false, "walls": true, "priority": 0, "roofColor": "#202020", "floorColor": "#ff4747", "roofHeight": 2.5, "wallsColor": "#dcdcdc", "wallsWidth": 0.1, "wallsHeight": 2.5}, "b92b815d-9572-4884-a122-b5b84bc48fe8": {"roof": false, "floor": true, "solid": false, "walls": true, "priority": 10, "roofColor": "#202020", "floorColor": "#ffffff", "roofHeight": 2.5, "wallsColor": "#dcdddc", "wallsWidth": 0.1, "wallsHeight": 2.5}, "be1c1c2a-7332-4491-b982-d2ba983d13a3": {"roof": false, "floor": true, "solid": false, "walls": true, "priority": 10, "roofColor": "#202020", "floorColor": "#eeeeee", "roofHeight": 2.5, "wallsColor": "#dcdddc", "wallsWidth": 0.1, "wallsHeight": 2.5}}, "elevator": {"roof": true, "floor": true, "solid": false, "walls": true, "priority": 10, "roofColor": "#c4d9df", "floorColor": "#d7ecf1", "roofHeight": 2.5, "wallsColor": "#b2c8ce", "wallsWidth": 0.1, "wallsHeight": 2.5}, "restroom": {"roof": true, "floor": true, "solid": false, "walls": true, "priority": 10, "roofColor": "#d1d6e6", "floorColor": "#d1d6e6", "roofHeight": 2.5, "wallsColor": "#d1d6e6", "wallsWidth": 0.1, "wallsHeight": 2.5}, "security": {"floor": true, "priority": 100, "floorColor": "#fce6e8"}, "Aerodrome": {"roof": false, "floor": true, "solid": false, "walls": false, "priority": 0, "roofColor": "#202020", "floorColor": "#ededed", "roofHeight": 2.5, "wallsColor": "#a0a0a0", "wallsWidth": 0.1, "wallsHeight": 2.5}, "carrental": {"roof": false, "floor": true, "solid": false, "walls": false, "priority": 11, "roofColor": "#202020", "floorColor": "#f2f2f2", "roofHeight": 2.5, "wallsColor": "#dcdddc", "wallsWidth": 0.1, "wallsHeight": 2.5}, "escalator": {"roof": false, "floor": true, "solid": false, "walls": true, "priority": 10, "roofColor": "#c4d9df", "floorColor": "#d7ecf1", "wallsColor": "#b2c8ce", "wallsHeight": 0.5}, "furniture": {"floor": true, "solid": false, "walls": true, "priority": 10, "floorColor": "#d9dce7", "wallsColor": "#c7cbdd", "wallsHeight": 0.01}, "nonpublic": {"roof": true, "floor": false, "solid": true, "walls": true, "priority": 10, "roofColor": "#e8e8e8", "floorColor": "#606060", "roofHeight": 2.5, "wallsColor": "#dcdddc", "wallsWidth": 0.1, "wallsHeight": 2.5}, "structure": {"roof": true, "floor": false, "solid": true, "walls": true, "priority": 10, "roofColor": "#e8e8e8", "floorColor": "#606060", "roofHeight": 2.5, "wallsColor": "#dcdddc", "wallsWidth": 0.1, "wallsHeight": 2.5}, "Minor Road": {"roof": false, "floor": true, "solid": false, "walls": false, "priority": 0, "roofColor": "#202020", "floorColor": "#f7f7f7", "roofHeight": 2.5, "wallsColor": "#a0a0a0", "wallsWidth": 0.1, "wallsHeight": 2.5}, "foodservice": {"roof": false, "floor": true, "solid": false, "walls": true, "priority": 10, "roofColor": "#202020", "floorColor": "#e9edf1", "roofHeight": 2.5, "wallsColor": "#dcdddc", "wallsWidth": 0.1, "wallsHeight": 2.5}, "immigration": {"roof": false, "floor": false, "solid": false, "walls": false, "priority": 100, "roofColor": "#202020", "floorColor": "#fce6e8", "roofHeight": 2.5, "wallsColor": "#a0a0a0", "wallsWidth": 0.1, "wallsHeight": 2.5}, "mothersroom": {"roof": true, "floor": true, "solid": false, "walls": true, "priority": 10, "roofColor": "#d1d6e6", "floorColor": "#d1d6e6", "roofHeight": 2.5, "wallsColor": "#d1d6e6", "wallsWidth": 0.1, "wallsHeight": 2.5}, "opentobelow": {"roof": false, "floor": true, "solid": false, "walls": false, "priority": 10, "roofColor": "#ece4d6", "floorColor": "#e4ecef", "roofHeight": 2.5, "wallsColor": "#dcdddc", "wallsWidth": 0.1, "wallsHeight": 2.5}, "unspecified": {"roof": false, "floor": true, "solid": false, "walls": true, "priority": 0, "roofColor": "#202020", "floorColor": "#e9edf1", "roofHeight": 2.5, "wallsColor": "#dcdddc", "wallsWidth": 0.1, "wallsHeight": 2.5}, "baggageclaim": {"roof": false, "floor": false, "solid": false, "walls": false, "priority": 10, "roofColor": "#202020", "floorColor": "#d9dce7", "roofHeight": 2.5, "wallsColor": "#c9d1dd", "wallsWidth": 0.1, "wallsHeight": 0.5}, "checkin.desk": {"roof": false, "floor": true, "solid": false, "walls": true, "priority": 15, "roofColor": "#202020", "floorColor": "#f2f2f2", "roofHeight": 2.5, "wallsColor": "#dcdddc", "wallsWidth": 0.1, "wallsHeight": 0.5}, "movingwalkway": {"roof": false, "floor": true, "solid": false, "walls": true, "priority": 10, "roofColor": "#202020", "floorColor": "#d7ecf1", "roofHeight": 2.5, "wallsColor": "#b2c8ce", "wallsWidth": 0.1, "wallsHeight": 0.7}, "privatelounge": {"roof": false, "floor": true, "solid": false, "walls": true, "priority": 10, "roofColor": "#202020", "floorColor": "#e9edf1", "roofHeight": 2.5, "wallsColor": "#dcdddc", "wallsWidth": 0.1, "wallsHeight": 2.5}, "restroom.male": {"roof": true, "floor": true, "solid": false, "walls": true, "priority": 10, "roofColor": "#d1d6e6", "floorColor": "#d1d6e6", "roofHeight": 2.5, "wallsColor": "#d1d6e6", "wallsWidth": 0.1, "wallsHeight": 2.5}, "baggagecarousel": {"roof": false, "floor": true, "solid": false, "walls": true, "priority": 10, "roofColor": "#202020", "floorColor": "#d9dce7", "roofHeight": 2.5, "wallsColor": "#c2cad5", "wallsWidth": 0.1, "wallsHeight": 0.5}, "restroom.female": {"roof": true, "floor": true, "solid": false, "walls": true, "priority": 10, "roofColor": "#d1d6e6", "floorColor": "#d1d6e6", "roofHeight": 2.5, "wallsColor": "#d1d6e6", "wallsWidth": 0.1, "wallsHeight": 2.5}, "restroom.unisex": {"roof": true, "floor": true, "solid": false, "walls": true, "priority": 10, "roofColor": "#d1d6e6", "floorColor": "#d1d6e6", "roofHeight": 2.5, "wallsColor": "#d1d6e6", "wallsWidth": 0.1, "wallsHeight": 2.5}, "Building_basemap": {"roof": false, "floor": true, "solid": false, "walls": false, "priority": 0, "roofColor": "#202020", "floorColor": "#ece4d6", "roofHeight": 2.5, "wallsColor": "#a0a0a0", "wallsWidth": 0.1, "wallsHeight": 2.5}, "84578764-8448-4191-b2af-f518cbfbafe7": {"roof": false, "floor": false, "solid": false, "walls": true, "priority": 0, "roofColor": "#202020", "floorColor": "#ff4747", "roofHeight": 2.5, "wallsColor": "#dcdcdc", "wallsWidth": 0.1, "wallsHeight": 2.5}, "b92b815d-9572-4884-a122-b5b84bc48fe8": {"roof": false, "floor": true, "solid": false, "walls": true, "priority": 10, "roofColor": "#202020", "floorColor": "#ffffff", "roofHeight": 2.5, "wallsColor": "#dcdddc", "wallsWidth": 0.1, "wallsHeight": 2.5}, "be1c1c2a-7332-4491-b982-d2ba983d13a3": {"roof": false, "floor": true, "solid": false, "walls": true, "priority": 10, "roofColor": "#202020", "floorColor": "#eeeeee", "roofHeight": 2.5, "wallsColor": "#dcdddc", "wallsWidth": 0.1, "wallsHeight": 2.5}}